{
  "segment_id": "root",
  "segment_steps": [
    {
      "name": "step_qonnx_to_finn"
    }
  ],
  "branch_decision": null,
  "is_branch_point": true,
  "children": {
    "cleanup_opt0": {
      "segment_id": "cleanup_opt0",
      "segment_steps": [
        {
          "transforms": [
            "RemoveIdentityOps",
            "RemoveUnusedTensors",
            "GiveUniqueNodeNames"
          ],
          "stage_name": "cleanup"
        }
      ],
      "branch_decision": "cleanup_opt0",
      "is_branch_point": true,
      "children": {
        "optional_step_opt0": {
          "segment_id": "cleanup_opt0/optional_step_opt0",
          "segment_steps": [
            {
              "transforms": [
                "FoldConstants",
                "InferShapes",
                "GiveUniqueParameterTensors",
                "RemoveUnusedNodes"
              ],
              "stage_name": "optional_step"
            },
            {
              "name": "step_create_dataflow_partition"
            },
            {
              "name": "step_generate_estimate_reports"
            }
          ],
          "branch_decision": "optional_step_opt0",
          "is_branch_point": false,
          "children": {}
        },
        "optional_step_opt1": {
          "segment_id": "cleanup_opt0/optional_step_opt1",
          "segment_steps": [
            {
              "transforms": [
                "InferShapes",
                "GiveUniqueParameterTensors",
                "RemoveUnusedNodes"
              ],
              "stage_name": "optional_step"
            },
            {
              "name": "step_create_dataflow_partition"
            },
            {
              "name": "step_generate_estimate_reports"
            }
          ],
          "branch_decision": "optional_step_opt1",
          "is_branch_point": false,
          "children": {}
        }
      }
    },
    "cleanup_opt1": {
      "segment_id": "cleanup_opt1",
      "segment_steps": [
        {
          "transforms": [
            "RemoveIdentityOps",
            "RemoveUnusedTensors",
            "GiveRandomTensorNames"
          ],
          "stage_name": "cleanup"
        }
      ],
      "branch_decision": "cleanup_opt1",
      "is_branch_point": true,
      "children": {
        "optional_step_opt0": {
          "segment_id": "cleanup_opt1/optional_step_opt0",
          "segment_steps": [
            {
              "transforms": [
                "FoldConstants",
                "InferShapes",
                "GiveUniqueParameterTensors",
                "RemoveUnusedNodes"
              ],
              "stage_name": "optional_step"
            },
            {
              "name": "step_create_dataflow_partition"
            },
            {
              "name": "step_generate_estimate_reports"
            }
          ],
          "branch_decision": "optional_step_opt0",
          "is_branch_point": false,
          "children": {}
        },
        "optional_step_opt1": {
          "segment_id": "cleanup_opt1/optional_step_opt1",
          "segment_steps": [
            {
              "transforms": [
                "InferShapes",
                "GiveUniqueParameterTensors",
                "RemoveUnusedNodes"
              ],
              "stage_name": "optional_step"
            },
            {
              "name": "step_create_dataflow_partition"
            },
            {
              "name": "step_generate_estimate_reports"
            }
          ],
          "branch_decision": "optional_step_opt1",
          "is_branch_point": false,
          "children": {}
        }
      }
    }
  }
}